{"main-code_file:///Users/zhengjianpei/Desktop/zfbDemo/game.json":{"cursorState":[{"inSelectionMode":false,"selectionStart":{"lineNumber":1,"column":1},"position":{"lineNumber":1,"column":1}}],"viewState":{"scrollLeft":0,"firstPosition":{"lineNumber":1,"column":1},"firstPositionDeltaTop":0},"contributionsState":{"editor.contrib.wordHighlighter":false,"editor.contrib.folding":{"collapsedRegions":null,"lineCount":4,"provider":"indent"}}},"main-code_file:///Users/zhengjianpei/Desktop/useful_demo/alipay_demo/demos/audio.js":{"cursorState":[{"inSelectionMode":false,"selectionStart":{"lineNumber":1,"column":1},"position":{"lineNumber":1,"column":1}}],"viewState":{"scrollLeft":0,"firstPosition":{"lineNumber":1,"column":1},"firstPositionDeltaTop":0},"contributionsState":{"editor.contrib.wordHighlighter":false,"editor.contrib.folding":{"collapsedRegions":null,"lineCount":36,"provider":"indent"}}},"main-code_file:///Users/zhengjianpei/Desktop/useful_demo/alipay_demo/demos/repeatlyLoadAudio.js":{"cursorState":[{"inSelectionMode":false,"selectionStart":{"lineNumber":1,"column":1},"position":{"lineNumber":1,"column":1}}],"viewState":{"scrollLeft":0,"firstPosition":{"lineNumber":1,"column":1},"firstPositionDeltaTop":0},"contributionsState":{"editor.contrib.wordHighlighter":false,"editor.contrib.folding":{"collapsedRegions":null,"lineCount":14,"provider":"indent"}}},"main-code_file:///Users/zhengjianpei/Desktop/useful_demo/alipay_demo/demos/acceleration.js":{"cursorState":[{"inSelectionMode":false,"selectionStart":{"lineNumber":1,"column":1},"position":{"lineNumber":1,"column":1}}],"viewState":{"scrollLeft":0,"firstPosition":{"lineNumber":1,"column":1},"firstPositionDeltaTop":0},"contributionsState":{"editor.contrib.wordHighlighter":false,"editor.contrib.folding":{"collapsedRegions":null,"lineCount":23,"provider":"indent"}}},"main-code_file:///Users/zhengjianpei/Desktop/useful_demo/alipay_demo/res/bgm.mp3":{"cursorState":[{"inSelectionMode":false,"selectionStart":{"lineNumber":1,"column":1},"position":{"lineNumber":1,"column":1}}],"viewState":{"scrollLeft":0,"firstPosition":{"lineNumber":1,"column":1},"firstPositionDeltaTop":0},"contributionsState":{"editor.contrib.wordHighlighter":false,"editor.contrib.folding":{"collapsedRegions":null,"lineCount":2061,"provider":"indent"}}},"main-code_file:///Users/zhengjianpei/Desktop/useful_demo/alipay_demo/game.js":{"cursorState":[{"inSelectionMode":false,"selectionStart":{"lineNumber":53,"column":34},"position":{"lineNumber":53,"column":34}}],"viewState":{"scrollLeft":1,"firstPosition":{"lineNumber":41,"column":1},"firstPositionDeltaTop":-12},"contributionsState":{"editor.contrib.wordHighlighter":false,"editor.contrib.folding":{"collapsedRegions":null,"lineCount":53,"provider":"indent"}}},"main-code_file:///Users/zhengjianpei/Desktop/useful_demo/alipay_demo/demos/readBuffer.js":{"cursorState":[{"inSelectionMode":false,"selectionStart":{"lineNumber":4,"column":25},"position":{"lineNumber":4,"column":25}}],"viewState":{"scrollLeft":0,"firstPosition":{"lineNumber":1,"column":1},"firstPositionDeltaTop":0},"contributionsState":{"editor.contrib.wordHighlighter":false,"editor.contrib.folding":{"collapsedRegions":null,"lineCount":14,"provider":"indent"}}},"main-code_file:///Users/zhengjianpei/Desktop/useful_demo/alipay_demo/demos/fs_readFile.js":{"cursorState":[{"inSelectionMode":true,"selectionStart":{"lineNumber":25,"column":10},"position":{"lineNumber":15,"column":7}}],"viewState":{"scrollLeft":0,"firstPosition":{"lineNumber":6,"column":1},"firstPositionDeltaTop":-10},"contributionsState":{"editor.contrib.wordHighlighter":false,"editor.contrib.folding":{"collapsedRegions":null,"lineCount":31,"provider":"indent"}}},"main-code_file:///Users/zhengjianpei/Desktop/useful_demo/alipay_demo/game.json":{"cursorState":[{"inSelectionMode":false,"selectionStart":{"lineNumber":2,"column":35},"position":{"lineNumber":2,"column":35}}],"viewState":{"scrollLeft":0,"firstPosition":{"lineNumber":1,"column":1},"firstPositionDeltaTop":0},"contributionsState":{"editor.contrib.wordHighlighter":false,"editor.contrib.folding":{"collapsedRegions":null,"lineCount":4,"provider":"indent"}}},"main-code_file:///Users/zhengjianpei/Desktop/useful_demo/alipay_demo/demos/audioDuration.js":{"cursorState":[{"inSelectionMode":false,"selectionStart":{"lineNumber":1,"column":1},"position":{"lineNumber":1,"column":1}}],"viewState":{"scrollLeft":0,"firstPosition":{"lineNumber":1,"column":1},"firstPositionDeltaTop":0},"contributionsState":{"editor.contrib.wordHighlighter":false,"editor.contrib.folding":{"collapsedRegions":null,"lineCount":9,"provider":"indent"}}},"main-code_file:///Users/zhengjianpei/Desktop/useful_demo/alipay_demo/README.md":{"cursorState":[{"inSelectionMode":false,"selectionStart":{"lineNumber":1,"column":1},"position":{"lineNumber":1,"column":1}}],"viewState":{"scrollLeft":0,"firstPosition":{"lineNumber":1,"column":1},"firstPositionDeltaTop":0},"contributionsState":{"editor.contrib.wordHighlighter":false,"editor.contrib.folding":{"collapsedRegions":null,"lineCount":6,"provider":"indent"}}}}